__init__.py
mcss.py
mcss_api-0.0.2.dist-info/LICENSE
mcss_api-0.0.2.dist-info/METADATA
mcss_api-0.0.2.dist-info/WHEEL
mcss_api-0.0.2.dist-info/top_level.txt
mcss_api-0.0.2.dist-info/RECORD
