Metadata-Version: 2.1
Name: mcss-api
Version: 0.0.2
Summary: A library to easily access the MCSS api.
Author-email: Les Packages <les.packages@gmail.com>
License: MIT License        
Project-URL: Docs, https://coming.soon/
Classifier: Programming Language :: Python :: 3
Classifier: Programming Language :: Python :: 2.7
Classifier: License :: OSI Approved :: MIT License
Classifier: Operating System :: OS Independent
Requires-Python: >=3.7
License-File: LICENSE
